openagent1/__init__.py
openagent1/open_agent.py
openagent1-0.0.11.dist-info/METADATA
openagent1-0.0.11.dist-info/WHEEL
openagent1-0.0.11.dist-info/licenses/LICENSE
openagent1-0.0.11.dist-info/RECORD
