Metadata-Version: 2.4
Name: openagent1
Version: 0.0.11
Summary: An extensible transparent agent architecture.
Project-URL: Homepage, https://github.com/openagent1/openagent
Author-email: Eddy <86904062+eddyjin1@users.noreply.github.com>
License: AGPL-3.0-or-later
License-File: LICENSE
Classifier: License :: OSI Approved :: GNU Affero General Public License v3 or later (AGPLv3+)
Classifier: Operating System :: OS Independent
Classifier: Programming Language :: Python :: 3
Requires-Python: >=3.9
